amka_py/__init__.py
amka_py/amka.py
amka_py-0.1.0.dist-info/LICENSE
amka_py-0.1.0.dist-info/WHEEL
amka_py-0.1.0.dist-info/METADATA
amka_py-0.1.0.dist-info/RECORD
