Metadata-Version: 2.1
Name: amka-py
Version: 0.1.0
Summary: A validator for greek social security number (AMKA)
Home-page: https://github.com/zoispag/amka-py
License: MIT
Author: Zois Pagoulatos
Author-email: zpagoulatos@hotmail.com
Requires-Python: >=3.7,<4.0
Classifier: License :: OSI Approved :: MIT License
Classifier: Programming Language :: Python :: 3
Classifier: Programming Language :: Python :: 3.7
Classifier: Programming Language :: Python :: 3.8
Classifier: Programming Language :: Python :: 3.9
Project-URL: Repository, https://github.com/zoispag/amka-py
